[
  {
    "chapterName": "Delta Delta",
    "university": "Purdue University",
    "members": [
      {
        "firstName": "Alexander",
        "lastName": "An",
        "fullName": "Alexander An",
        "chapterGreekLetters": "Delta Delta",
        "memberType": "Undergrad",
        "status": "Active",
        "email": "alexanboss2@gmail.com",
        "phone": "6505200072"
      },
      {
        "firstName": "Tyler",
        "lastName": "Baker",
        "fullName": "Tyler Dale Baker",
        "chapterGreekLetters": "Delta Delta",
        "memberType": "Undergrad",
        "status": "Active",
        "email": "tylerbaker118@yahoo.com",
        "phone": "7657304868"
      },
      {
        "firstName": "Max",
        "lastName": "Baltz",
        "fullName": "Max Martin Baltz",
        "chapterGreekLetters": "Delta Delta",
        "memberType": "Undergrad",
        "status": "Active",
        "email": "mmbindy01@outlook.com",
        "phone": "3177796275"
      },
      {
        "firstName": "Eric",
        "lastName": "Bartczak",
        "fullName": "Eric Marek Bartczak",
        "chapterGreekLetters": "Delta Delta",
        "memberType": "Undergrad",
        "status": "Active",
        "email": "ebiman9726@gmail.com",
        "phone": "Hidden"
      },
      {
        "firstName": "Kyle",
        "lastName": "Bastian",
        "fullName": "Kyle Edward Bastian",
        "chapterGreekLetters": "Delta Delta",
        "memberType": "Undergrad",
        "status": "Active",
        "email": "kebastian2021@gmail.com",
        "phone": "(317) 766-1935"
      },
      {
        "firstName": "Nick",
        "lastName": "Belby",
        "fullName": "Nick Belby",
        "chapterGreekLetters": "Delta Delta",
        "memberType": "Undergrad",
        "status": "Active",
        "email": "nbelby05@gmail.com",
        "phone": "3177375410"
      },
      {
        "firstName": "Nathan",
        "lastName": "Blied",
        "fullName": "Nathan Gregory Blied",
        "chapterGreekLetters": "Delta Delta",
        "memberType": "Undergrad",
        "status": "Active",
        "email": "nathanblied@gmail.com",
        "phone": "269-519-9587"
      },
      {
        "firstName": "Eric",
        "lastName": "Boyd",
        "fullName": "Eric Scott Boyd",
        "chapterGreekLetters": "Delta Delta",
        "memberType": "Undergrad",
        "status": "Active",
        "email": "ericboyd2004611@gmail.com",
        "phone": "(260) 440-0602"
      },
      {
        "firstName": "Ian",
        "lastName": "Brady",
        "fullName": "Ian Alexander Brady",
        "chapterGreekLetters": "Delta Delta",
        "memberType": "Undergrad",
        "status": "Active",
        "email": "ianbrady05@icloud.com",
        "phone": "619-307-9975"
      },
      {
        "firstName": "Max",
        "lastName": "Bratchie",
        "fullName": "Max Robert Bratchie",
        "chapterGreekLetters": "Delta Delta",
        "memberType": "Undergrad",
        "status": "Active",
        "email": "maxbratchie@gmail.com",
        "phone": "(631) 609-1088"
      },
      {
        "firstName": "Austin",
        "lastName": "Brooks",
        "fullName": "Austin James Brooks",
        "chapterGreekLetters": "Delta Delta",
        "memberType": "Undergrad",
        "status": "Active",
        "email": "brooksaustin2006@yahoo.com",
        "phone": "(317) 501-0079"
      },
      {
        "firstName": "Nolan",
        "lastName": "Buckman",
        "fullName": "Nolan Michael Buckman",
        "chapterGreekLetters": "Delta Delta",
        "memberType": "Undergrad",
        "status": "Active",
        "email": "nolanbuckman07@gmail.com",
        "phone": "(317) 437-1888"
      },
      {
        "firstName": "Preston",
        "lastName": "Bunch",
        "fullName": "Preston Bunch",
        "chapterGreekLetters": "Delta Delta",
        "memberType": "Undergrad",
        "status": "Active",
        "email": "prestonbunch@icloud.com",
        "phone": "3179035061"
      },
      {
        "firstName": "Robert",
        "lastName": "Burt",
        "fullName": "Robert William Burt",
        "chapterGreekLetters": "Delta Delta",
        "memberType": "Undergrad",
        "status": "Active",
        "email": "burtrobbie23@gmail.com",
        "phone": "3179009302"
      },
      {
        "firstName": "Ronald",
        "lastName": "Carpinella",
        "fullName": "Ronald Andrew Carpinella",
        "chapterGreekLetters": "Delta Delta",
        "memberType": "Undergrad",
        "status": "Active",
        "email": "racarpi3@gmail.com",
        "phone": "(404) 951-8973"
      },
      {
        "firstName": "Jude",
        "lastName": "Carsten",
        "fullName": "Jude Christopher Carsten",
        "chapterGreekLetters": "Delta Delta",
        "memberType": "Undergrad",
        "status": "Active",
        "email": "carstencjude@gmail.com",
        "phone": "260-388-9213"
      },
      {
        "firstName": "Brady",
        "lastName": "Cavanuagh",
        "fullName": "Brady Christopher Cavanuagh",
        "chapterGreekLetters": "Delta Delta",
        "memberType": "Undergrad",
        "status": "Active",
        "email": "bradycav42@gmail.com",
        "phone": "(219)307-3509"
      },
      {
        "firstName": "Aiden",
        "lastName": "Clinton",
        "fullName": "Aiden Adam Clinton",
        "chapterGreekLetters": "Delta Delta",
        "memberType": "Undergrad",
        "status": "Active",
        "email": "clintonaiden03@gmail.com",
        "phone": "(317) 864-3672"
      },
      {
        "firstName": "Matthew",
        "lastName": "Coleman",
        "fullName": "Matthew Thomas Coleman",
        "chapterGreekLetters": "Delta Delta",
        "memberType": "Undergrad",
        "status": "Active",
        "email": "mtcole2006@icloud.com",
        "phone": "8156858133"
      },
      {
        "firstName": "Owen",
        "lastName": "Coleman",
        "fullName": "Owen Andrew Coleman",
        "chapterGreekLetters": "Delta Delta",
        "memberType": "Undergrad",
        "status": "Active",
        "email": "owenandrewcoleman@hotmail.com",
        "phone": "(703) 395-4205"
      },
      {
        "firstName": "Parker",
        "lastName": "Coyle",
        "fullName": "Parker Coyle",
        "chapterGreekLetters": "Delta Delta",
        "memberType": "Undergrad",
        "status": "Active",
        "email": "parkercoyle8@gmail.com",
        "phone": "425-318-5178"
      },
      {
        "firstName": "Harold",
        "lastName": "DeMuyt",
        "fullName": "Harold Marek DeMuyt",
        "chapterGreekLetters": "Delta Delta",
        "memberType": "Undergrad",
        "status": "Active",
        "email": "harrydemuyt23@gmail.com",
        "phone": "(203) 685-2611"
      },
      {
        "firstName": "Wayne",
        "lastName": "Detwiler",
        "fullName": "Wayne Leon Detwiler",
        "chapterGreekLetters": "Delta Delta",
        "memberType": "Undergrad",
        "status": "Active",
        "email": "leodetwiler@gmail.com",
        "phone": "(703) 577-2882"
      },
      {
        "firstName": "Alexander",
        "lastName": "Dibble",
        "fullName": "Alexander James Dibble",
        "chapterGreekLetters": "Delta Delta",
        "memberType": "Undergrad",
        "status": "Active",
        "email": "dibblealex06@gmail.com",
        "phone": "(574) 518-0480"
      },
      {
        "firstName": "Thomas",
        "lastName": "DiMarco",
        "fullName": "Thomas Riley DiMarco",
        "chapterGreekLetters": "Delta Delta",
        "memberType": "Undergrad",
        "status": "Active",
        "email": "thomasrileydimarco@gmail.com",
        "phone": "224-775-2055"
      },
      {
        "firstName": "Miles",
        "lastName": "Ditto",
        "fullName": "Miles Bowman Ditto",
        "chapterGreekLetters": "Delta Delta",
        "memberType": "Undergrad",
        "status": "Active",
        "email": "milesditto06@gmail.com",
        "phone": "7654649031"
      },
      {
        "firstName": "Samuel",
        "lastName": "Drewry",
        "fullName": "Samuel Michael Drewry",
        "chapterGreekLetters": "Delta Delta",
        "memberType": "Undergrad",
        "status": "Active",
        "email": "sdrewry05@gmail.com",
        "phone": "317-778-0543"
      },
      {
        "firstName": "Nate",
        "lastName": "Dufilho",
        "fullName": "Nate James Dufilho",
        "chapterGreekLetters": "Delta Delta",
        "memberType": "Undergrad",
        "status": "Active",
        "email": "natedufilho7@gmail.com",
        "phone": "(972) 762-9818"
      },
      {
        "firstName": "Theophile",
        "lastName": "Dulcice",
        "fullName": "Theophile Dulcice",
        "chapterGreekLetters": "Delta Delta",
        "memberType": "Undergrad",
        "status": "Active",
        "email": "theodulcice@gmail.com",
        "phone": "Hidden"
      },
      {
        "firstName": "ethan",
        "lastName": "evans",
        "fullName": "ethan Sullivan evans",
        "chapterGreekLetters": "Delta Delta",
        "memberType": "Undergrad",
        "status": "Active",
        "email": "ethanevans165@gmail.com",
        "phone": "3178477496"
      },
      {
        "firstName": "Eliezer",
        "lastName": "Farnesi-Dubizh",
        "fullName": "Eliezer Rueven Farnesi-Dubizh",
        "chapterGreekLetters": "Delta Delta",
        "memberType": "Undergrad",
        "status": "Active",
        "email": "ed200419@gmail.com",
        "phone": "(347) 791-1300"
      },
      {
        "firstName": "Will",
        "lastName": "Fitzgibbons",
        "fullName": "Will Fitzgibbons",
        "chapterGreekLetters": "Delta Delta",
        "memberType": "Undergrad",
        "status": "Active",
        "email": "whfitz05@gmail.com",
        "phone": "5087685136"
      },
      {
        "firstName": "Andrew",
        "lastName": "Folkers",
        "fullName": "Andrew Patrick Folkers",
        "chapterGreekLetters": "Delta Delta",
        "memberType": "Undergrad",
        "status": "Active",
        "email": "drewfolkers@gmail.com",
        "phone": "(765) 414-8018"
      },
      {
        "firstName": "Emerson",
        "lastName": "Foote",
        "fullName": "Emerson William Foote",
        "chapterGreekLetters": "Delta Delta",
        "memberType": "Undergrad",
        "status": "Active",
        "email": "emersonfoote7@gmail.com",
        "phone": "(314) 295-1744"
      },
      {
        "firstName": "Peyton",
        "lastName": "Ford",
        "fullName": "Peyton Wayne Ford",
        "chapterGreekLetters": "Delta Delta",
        "memberType": "Undergrad",
        "status": "Active",
        "email": "peytonford2924@yahoo.com",
        "phone": "8125997916"
      },
      {
        "firstName": "Nathaniel",
        "lastName": "Galanti",
        "fullName": "Nathaniel Galanti",
        "chapterGreekLetters": "Delta Delta",
        "memberType": "Undergrad",
        "status": "Active",
        "email": "nate@galanti.org",
        "phone": "317-690-5175"
      },
      {
        "firstName": "Jackson",
        "lastName": "Gardzina",
        "fullName": "Jackson Clark Gardzina",
        "chapterGreekLetters": "Delta Delta",
        "memberType": "Undergrad",
        "status": "Active",
        "email": "jacksongardzina@icloud.com",
        "phone": "6154871291"
      },
      {
        "firstName": "Hayden",
        "lastName": "Garten",
        "fullName": "Hayden Christopher Garten",
        "chapterGreekLetters": "Delta Delta",
        "memberType": "Undergrad",
        "status": "Active",
        "email": "haydengarten@gmail.com",
        "phone": "8125953448"
      },
      {
        "firstName": "Jackson",
        "lastName": "Garvey",
        "fullName": "Jackson Harris Garvey",
        "chapterGreekLetters": "Delta Delta",
        "memberType": "Undergrad",
        "status": "Active",
        "email": "jacksongarvey@icloud.com",
        "phone": "(262) 899-9434"
      },
      {
        "firstName": "Oliver",
        "lastName": "Gebke",
        "fullName": "Oliver Raymond Gebke",
        "chapterGreekLetters": "Delta Delta",
        "memberType": "Undergrad",
        "status": "Active",
        "email": "oegebke@gmail.com",
        "phone": "3175086877"
      },
      {
        "firstName": "Dillon",
        "lastName": "Glass",
        "fullName": "Dillon Lee Glass",
        "chapterGreekLetters": "Delta Delta",
        "memberType": "Undergrad",
        "status": "Active",
        "email": "dillonlglass@gmail.com",
        "phone": "(317) 910-9269"
      },
      {
        "firstName": "Max",
        "lastName": "Glowacki",
        "fullName": "Max Ryan Glowacki",
        "chapterGreekLetters": "Delta Delta",
        "memberType": "Undergrad",
        "status": "Active",
        "email": "mrglow21@gmail.com",
        "phone": "2194071877"
      },
      {
        "firstName": "Bryce",
        "lastName": "Gray",
        "fullName": "Bryce Donald Gray",
        "chapterGreekLetters": "Delta Delta",
        "memberType": "Undergrad",
        "status": "Active",
        "email": "bdgray2003@gmail.com",
        "phone": "(925) 290-5596"
      },
      {
        "firstName": "Sawyer",
        "lastName": "Grimes",
        "fullName": "Sawyer Warren Grimes",
        "chapterGreekLetters": "Delta Delta",
        "memberType": "Undergrad",
        "status": "Active",
        "email": "saw.grimes@gmail.com",
        "phone": "5749711514"
      },
      {
        "firstName": "Jack",
        "lastName": "Grote",
        "fullName": "Jack Deeves Grote",
        "chapterGreekLetters": "Delta Delta",
        "memberType": "Undergrad",
        "status": "Active",
        "email": "jack.grote9@gmail.com",
        "phone": "(812) 701-4151"
      },
      {
        "firstName": "Andrew",
        "lastName": "Happ",
        "fullName": "Andrew Christopher Happ",
        "chapterGreekLetters": "Delta Delta",
        "memberType": "Undergrad",
        "status": "Active",
        "email": "andyhapp31@outlook.com",
        "phone": "412-443-8155"
      },
      {
        "firstName": "Matthew",
        "lastName": "Hauptner",
        "fullName": "Matthew Ted Hauptner",
        "chapterGreekLetters": "Delta Delta",
        "memberType": "Undergrad",
        "status": "Active",
        "email": "matthewhauptner@gmail.com",
        "phone": "330-840-4678"
      },
      {
        "firstName": "Thomas",
        "lastName": "Henry",
        "fullName": "Thomas Edward Henry",
        "chapterGreekLetters": "Delta Delta",
        "memberType": "Undergrad",
        "status": "Active",
        "email": "henryt493@yahoo.com",
        "phone": "7654270746"
      },
      {
        "firstName": "Luke",
        "lastName": "Hopkinson",
        "fullName": "Luke Michael Hopkinson",
        "chapterGreekLetters": "Delta Delta",
        "memberType": "Undergrad",
        "status": "Active",
        "email": "luke.m.hopkinson02@gmail.com",
        "phone": "(214) 971-1817"
      },
      {
        "firstName": "Joseph",
        "lastName": "Huntine",
        "fullName": "Joseph Francis Huntine",
        "chapterGreekLetters": "Delta Delta",
        "memberType": "Undergrad",
        "status": "Active",
        "email": "josephhuntine@gmail.com",
        "phone": "(317) 607-3530"
      },
      {
        "firstName": "Ryder",
        "lastName": "Hutton",
        "fullName": "Ryder Cade Hutton",
        "chapterGreekLetters": "Delta Delta",
        "memberType": "Undergrad",
        "status": "Active",
        "email": "ryderhutton33@gmail.com",
        "phone": "7204426760"
      },
      {
        "firstName": "Nicholas",
        "lastName": "Ingraffia",
        "fullName": "Nicholas Michael Ingraffia",
        "chapterGreekLetters": "Delta Delta",
        "memberType": "Undergrad",
        "status": "Active",
        "email": "nickingraffia@gmail.com",
        "phone": "(630) 915-0914"
      },
      {
        "firstName": "Jacob",
        "lastName": "Kleeman",
        "fullName": "Jacob P Kleeman",
        "chapterGreekLetters": "Delta Delta",
        "memberType": "Undergrad",
        "status": "Active",
        "email": "jacobkleeman@icloud.com",
        "phone": "3175184464"
      },
      {
        "firstName": "Jack",
        "lastName": "Knecht",
        "fullName": "Jack Thomas Knecht",
        "chapterGreekLetters": "Delta Delta",
        "memberType": "Undergrad",
        "status": "Active",
        "email": "jackknecht1@gmail.com",
        "phone": "(317) 601-7031"
      },
      {
        "firstName": "Grant",
        "lastName": "Koeneman",
        "fullName": "Grant parker Koeneman",
        "chapterGreekLetters": "Delta Delta",
        "memberType": "Undergrad",
        "status": "Active",
        "email": "koenemangrant@gmail.com",
        "phone": "3173498840"
      },
      {
        "firstName": "Ian",
        "lastName": "Kolbus",
        "fullName": "Ian Howard Kolbus",
        "chapterGreekLetters": "Delta Delta",
        "memberType": "Undergrad",
        "status": "Active",
        "email": "ian.kolbus@gmail.com",
        "phone": "317-993-7531"
      },
      {
        "firstName": "Jeremy",
        "lastName": "Krainin",
        "fullName": "Jeremy Asher Krainin",
        "chapterGreekLetters": "Delta Delta",
        "memberType": "Undergrad",
        "status": "Active",
        "email": "kraininfamily3@gmail.com",
        "phone": "4089130478"
      },
      {
        "firstName": "Michael",
        "lastName": "LaRocca",
        "fullName": "Michael LaRocca",
        "chapterGreekLetters": "Delta Delta",
        "memberType": "Undergrad",
        "status": "Active",
        "email": "michaellarocca2003@gmail.com",
        "phone": "(317) 417-0330"
      },
      {
        "firstName": "Liam",
        "lastName": "Lawson",
        "fullName": "Liam Tyler Lawson",
        "chapterGreekLetters": "Delta Delta",
        "memberType": "Undergrad",
        "status": "Active",
        "email": "lawsonatorlt@gmail.com",
        "phone": "4143034028"
      },
      {
        "firstName": "Jack",
        "lastName": "Lefebvre",
        "fullName": "Jack Christopher Lefebvre",
        "chapterGreekLetters": "Delta Delta",
        "memberType": "Undergrad",
        "status": "Active",
        "email": "lefebvrejack50@gmail.com",
        "phone": "317-363-9481"
      },
      {
        "firstName": "Alexander",
        "lastName": "Lefebvre",
        "fullName": "Alexander Garrett Lefebvre",
        "chapterGreekLetters": "Delta Delta",
        "memberType": "Undergrad",
        "status": "Active",
        "email": "aglefebvre25@gocathedral.com",
        "phone": "317-242-8987"
      },
      {
        "firstName": "Noah",
        "lastName": "Macias",
        "fullName": "Noah Macias",
        "chapterGreekLetters": "Delta Delta",
        "memberType": "Undergrad",
        "status": "Active",
        "email": "noahmacias15@gmail.com",
        "phone": "574370-1979"
      },
      {
        "firstName": "Shemaya",
        "lastName": "Magatti",
        "fullName": "Shemaya Magatti",
        "chapterGreekLetters": "Delta Delta",
        "memberType": "Undergrad",
        "status": "Active",
        "email": "magattishemaya@gmail.com",
        "phone": "5745388781"
      },
      {
        "firstName": "Nick",
        "lastName": "Marlin",
        "fullName": "Nick Samuel Marlin",
        "chapterGreekLetters": "Delta Delta",
        "memberType": "Undergrad",
        "status": "Active",
        "email": "nmarlini06@gmail.com",
        "phone": "3177497759"
      },
      {
        "firstName": "Matthew",
        "lastName": "Marrano",
        "fullName": "Matthew Marrano",
        "chapterGreekLetters": "Delta Delta",
        "memberType": "Undergrad",
        "status": "Active",
        "email": "matthewmarrano@icloud.com",
        "phone": "3173080473"
      },
      {
        "firstName": "Carter",
        "lastName": "Matthes",
        "fullName": "Carter Dean Matthes",
        "chapterGreekLetters": "Delta Delta",
        "memberType": "Undergrad",
        "status": "Active",
        "email": "matthescarter@gmail.com",
        "phone": "(314) 478-0120"
      },
      {
        "firstName": "Kane",
        "lastName": "McClurg",
        "fullName": "Kane Marco McClurg",
        "chapterGreekLetters": "Delta Delta",
        "memberType": "Undergrad",
        "status": "Active",
        "email": "kanemarco@icloud.com",
        "phone": "3176999644"
      },
      {
        "firstName": "Patrick",
        "lastName": "McPherson",
        "fullName": "Patrick Steven McPherson",
        "chapterGreekLetters": "Delta Delta",
        "memberType": "Undergrad",
        "status": "Active",
        "email": "patrickmcpherson05@gmail.com",
        "phone": "3178008655"
      },
      {
        "firstName": "Cameron",
        "lastName": "Milroy",
        "fullName": "Cameron Brian Milroy",
        "chapterGreekLetters": "Delta Delta",
        "memberType": "Undergrad",
        "status": "Active",
        "email": "cammilroy5@gmail.com",
        "phone": "(219) 728-9708"
      },
      {
        "firstName": "Skee",
        "lastName": "Mishler",
        "fullName": "Skee James Mishler",
        "chapterGreekLetters": "Delta Delta",
        "memberType": "Undergrad",
        "status": "Active",
        "email": "skeemishler@icloud.com",
        "phone": "(574)218-3039"
      },
      {
        "firstName": "Krue",
        "lastName": "Nagel",
        "fullName": "Krue Joseph Nagel",
        "chapterGreekLetters": "Delta Delta",
        "memberType": "Undergrad",
        "status": "Active",
        "email": "kruenagel04@gmail.com",
        "phone": "(260) 235-1481"
      },
      {
        "firstName": "Uzair",
        "lastName": "Nazeer",
        "fullName": "Uzair Umar Nazeer",
        "chapterGreekLetters": "Delta Delta",
        "memberType": "Undergrad",
        "status": "Active",
        "email": "uzair.nazeer@yahoo.com",
        "phone": "630-930-0129"
      },
      {
        "firstName": "James",
        "lastName": "Neff",
        "fullName": "James Joseph Neff",
        "chapterGreekLetters": "Delta Delta",
        "memberType": "Undergrad",
        "status": "Active",
        "email": "jamesneff07@gmail.com",
        "phone": "(925) 588-8459"
      },
      {
        "firstName": "Richard",
        "lastName": "Obert",
        "fullName": "Richard Charles Obert",
        "chapterGreekLetters": "Delta Delta",
        "memberType": "Undergrad",
        "status": "Active",
        "email": "obertrc11@gmail.com",
        "phone": "(858) 722-6597"
      },
      {
        "firstName": "Brett",
        "lastName": "Odgers",
        "fullName": "Brett Noah Odgers",
        "chapterGreekLetters": "Delta Delta",
        "memberType": "Undergrad",
        "status": "Active",
        "email": "brettodgers10@gmail.com",
        "phone": "3175607319"
      },
      {
        "firstName": "Mark",
        "lastName": "ODonnell",
        "fullName": "Mark Joseph ODonnell",
        "chapterGreekLetters": "Delta Delta",
        "memberType": "Undergrad",
        "status": "Active",
        "email": "mjo3soccer@yahoo.com",
        "phone": "(913) 602-4881"
      },
      {
        "firstName": "Alex",
        "lastName": "Orris",
        "fullName": "Alex Steven Orris",
        "chapterGreekLetters": "Delta Delta",
        "memberType": "Undergrad",
        "status": "Active",
        "email": "asorris06@gmail.com",
        "phone": "3179982280"
      },
      {
        "firstName": "Keertan",
        "lastName": "Palayam",
        "fullName": "Keertan Palayam",
        "chapterGreekLetters": "Delta Delta",
        "memberType": "Undergrad",
        "status": "Active",
        "email": "keertanpalayam@gmail.com",
        "phone": "267-753-5005"
      },
      {
        "firstName": "Drew",
        "lastName": "Parker",
        "fullName": "Drew Charles Parker",
        "chapterGreekLetters": "Delta Delta",
        "memberType": "Undergrad",
        "status": "Active",
        "email": "drew611@icloud.com",
        "phone": "(317) 800-3825"
      },
      {
        "firstName": "Heemir",
        "lastName": "Patel",
        "fullName": "Heemir Nainesh Patel",
        "chapterGreekLetters": "Delta Delta",
        "memberType": "Undergrad",
        "status": "Active",
        "email": "heemirnpatel@gmail.com",
        "phone": "(541) 840-2208"
      },
      {
        "firstName": "Daniel",
        "lastName": "Queroz",
        "fullName": "Daniel Mateo Queroz",
        "chapterGreekLetters": "Delta Delta",
        "memberType": "Undergrad",
        "status": "Active",
        "email": "dmqueroz@outlook.com",
        "phone": "2193234108"
      },
      {
        "firstName": "Jack",
        "lastName": "Ramsey",
        "fullName": "Jack White Ramsey",
        "chapterGreekLetters": "Delta Delta",
        "memberType": "Undergrad",
        "status": "Active",
        "email": "jackwramsey12@gmail.com",
        "phone": "(404) 538-4617"
      },
      {
        "firstName": "Erik",
        "lastName": "Raume",
        "fullName": "Erik James Raume",
        "chapterGreekLetters": "Delta Delta",
        "memberType": "Undergrad",
        "status": "Active",
        "email": "erikr@spectrumcolor.com",
        "phone": "904-806-9221"
      },
      {
        "firstName": "Robert",
        "lastName": "Renner",
        "fullName": "Robert Davis Renner",
        "chapterGreekLetters": "Delta Delta",
        "memberType": "Undergrad",
        "status": "Active",
        "email": "rdavisrenner@gmail.com",
        "phone": "6157627504"
      },
      {
        "firstName": "John",
        "lastName": "Reynolds",
        "fullName": "John Douglas Reynolds",
        "chapterGreekLetters": "Delta Delta",
        "memberType": "Undergrad",
        "status": "Active",
        "email": "johnreynz482@gmail.com",
        "phone": "3179194309"
      },
      {
        "firstName": "Mitchell",
        "lastName": "Rittman",
        "fullName": "Mitchell Louis Rittman",
        "chapterGreekLetters": "Delta Delta",
        "memberType": "Undergrad",
        "status": "Active",
        "email": "mitch.rittman@gmail.com",
        "phone": "(317) 997-6110"
      },
      {
        "firstName": "Aviv",
        "lastName": "Shakked",
        "fullName": "Aviv Liam Shakked",
        "chapterGreekLetters": "Delta Delta",
        "memberType": "Undergrad",
        "status": "Active",
        "email": "avivliamshakked@gmail.com",
        "phone": "4153604002"
      },
      {
        "firstName": "Jack",
        "lastName": "Shertzer",
        "fullName": "Jack Michael Shertzer",
        "chapterGreekLetters": "Delta Delta",
        "memberType": "Undergrad",
        "status": "Active",
        "email": "jackshertzer@gmail.com",
        "phone": "3179608823"
      },
      {
        "firstName": "Owen",
        "lastName": "Smith",
        "fullName": "Owen Clarke Smith",
        "chapterGreekLetters": "Delta Delta",
        "memberType": "Undergrad",
        "status": "Active",
        "email": "ocsmith0624@gmail.com",
        "phone": "2242138933"
      },
      {
        "firstName": "Joseph",
        "lastName": "Spragnuolo",
        "fullName": "Joseph Brady Spragnuolo",
        "chapterGreekLetters": "Delta Delta",
        "memberType": "Undergrad",
        "status": "Active",
        "email": "joeyspagnuolo@icloud.com",
        "phone": "3177970628"
      },
      {
        "firstName": "Sam",
        "lastName": "Stearns",
        "fullName": "Sam Stearns",
        "chapterGreekLetters": "Delta Delta",
        "memberType": "Undergrad",
        "status": "Active",
        "email": "szstearns7@gmail.com",
        "phone": "4083008197"
      },
      {
        "firstName": "John",
        "lastName": "Streadham",
        "fullName": "John Micheal Streadham",
        "chapterGreekLetters": "Delta Delta",
        "memberType": "Undergrad",
        "status": "Active",
        "email": "jacksteadham@yahoo.com",
        "phone": "3179877669"
      },
      {
        "firstName": "Kevin",
        "lastName": "Sweeney",
        "fullName": "Kevin James Sweeney",
        "chapterGreekLetters": "Delta Delta",
        "memberType": "Undergrad",
        "status": "Active",
        "email": "kevinjsweeney33@gmail.com",
        "phone": "(317) 764-6411"
      },
      {
        "firstName": "Wade",
        "lastName": "Sweet",
        "fullName": "Wade Allen Sweet",
        "chapterGreekLetters": "Delta Delta",
        "memberType": "Undergrad",
        "status": "Active",
        "email": "sweet.wade2006@gmail.com",
        "phone": "3175601391"
      },
      {
        "firstName": "Clark",
        "lastName": "Sweet",
        "fullName": "Clark Sweet",
        "chapterGreekLetters": "Delta Delta",
        "memberType": "Undergrad",
        "status": "Active",
        "email": "sweet.clark2003@gmail.com",
        "phone": "(317) 617-3707"
      },
      {
        "firstName": "Arjun",
        "lastName": "Talwar",
        "fullName": "Arjun Khanna Talwar",
        "chapterGreekLetters": "Delta Delta",
        "memberType": "Undergrad",
        "status": "Active",
        "email": "arjunktals@gmail.com",
        "phone": "3176041939"
      },
      {
        "firstName": "Jackson",
        "lastName": "Theobald",
        "fullName": "Jackson Thomas Theobald",
        "chapterGreekLetters": "Delta Delta",
        "memberType": "Undergrad",
        "status": "Active",
        "email": "jacksonttheobald@gmail.com",
        "phone": "3173161010"
      },
      {
        "firstName": "Lucas",
        "lastName": "Toppe",
        "fullName": "Lucas Isaiah Toppe",
        "chapterGreekLetters": "Delta Delta",
        "memberType": "Undergrad",
        "status": "Active",
        "email": "ltoppe@hotmail.com",
        "phone": "812-599-3015"
      },
      {
        "firstName": "Robert",
        "lastName": "Tully",
        "fullName": "Robert Tully",
        "chapterGreekLetters": "Delta Delta",
        "memberType": "Undergrad",
        "status": "Active",
        "email": "robbycliftontully@gmail.com",
        "phone": "317-616-8767"
      },
      {
        "firstName": "Tobey",
        "lastName": "Uhm",
        "fullName": "Tobey Andrew Uhm",
        "chapterGreekLetters": "Delta Delta",
        "memberType": "Undergrad",
        "status": "Active",
        "email": "tobeyuhm@gmail.com",
        "phone": "(312) 203-6194"
      },
      {
        "firstName": "Trevor",
        "lastName": "White",
        "fullName": "Trevor White",
        "chapterGreekLetters": "Delta Delta",
        "memberType": "Undergrad",
        "status": "Active",
        "email": "tcwrocks1017@gmail.com",
        "phone": "3174001936"
      },
      {
        "firstName": "Ryan",
        "lastName": "Williams",
        "fullName": "Ryan Williams",
        "chapterGreekLetters": "Delta Delta",
        "memberType": "Undergrad",
        "status": "Active",
        "email": "rcwill1534@gmail.com",
        "phone": "4243529999"
      },
      {
        "firstName": "Jamar",
        "lastName": "Wright",
        "fullName": "Jamar Wright",
        "chapterGreekLetters": "Delta Delta",
        "memberType": "Undergrad",
        "status": "Active",
        "email": "jamarnwright27@gmail.com",
        "phone": "8126971974"
      },
      {
        "firstName": "Saif",
        "lastName": "Zagha",
        "fullName": "Saif Zagha",
        "chapterGreekLetters": "Delta Delta",
        "memberType": "Undergrad",
        "status": "Active",
        "email": "saifzagha2@gmail.com",
        "phone": "727-608-3946"
      },
      {
        "firstName": "Joshua",
        "lastName": "Zhang",
        "fullName": "Joshua Zhiliang Zhang",
        "chapterGreekLetters": "Delta Delta",
        "memberType": "Undergrad",
        "status": "Active",
        "email": "zjosh0437@gmail.com",
        "phone": "(720) 724-0927"
      }
    ]
  }
]