[
  {
    "chapterName": "Kappa Iota",
    "university": "Southern Utah University",
    "members": [
      {
        "firstName": "Jonas",
        "lastName": "Anderson",
        "fullName": "Jonas Michael Anderson",
        "chapterGreekLetters": "Kappa Iota",
        "memberType": "Undergrad",
        "status": "Active",
        "email": "thejdog323@gmail.com",
        "phone": "8016166260"
      },
      {
        "firstName": "Thomas",
        "lastName": "Bunting",
        "fullName": "Thomas James Bunting",
        "chapterGreekLetters": "Kappa Iota",
        "memberType": "Undergrad",
        "status": "Active",
        "email": "thomasjbunt21@gmail.com",
        "phone": "435-592-6462"
      },
      {
        "firstName": "Oscar",
        "lastName": "Butters",
        "fullName": "Oscar Douglas Butters",
        "chapterGreekLetters": "Kappa Iota",
        "memberType": "Undergrad",
        "status": "Active",
        "email": "oscarbutters9@gmail.com",
        "phone": "(801) 696-5857"
      },
      {
        "firstName": "Alex",
        "lastName": "Calderon-Jensen",
        "fullName": "Alex Jorge Calderon-Jensen",
        "chapterGreekLetters": "Kappa Iota",
        "memberType": "Undergrad",
        "status": "Active",
        "email": "alexcj.business@gmail.com",
        "phone": "4156839407"
      },
      {
        "firstName": "Channing",
        "lastName": "Caldwell",
        "fullName": "Channing Caldwell",
        "chapterGreekLetters": "Kappa Iota",
        "memberType": "Undergrad",
        "status": "Active",
        "email": "chanman13360@gmail.com",
        "phone": "9035173777"
      },
      {
        "firstName": "Talmage",
        "lastName": "Candland",
        "fullName": "Talmage Candland",
        "chapterGreekLetters": "Kappa Iota",
        "memberType": "Undergrad",
        "status": "Active",
        "email": "talmagecandland2@gmail.com",
        "phone": "4804361359"
      },
      {
        "firstName": "Treyvin",
        "lastName": "Collum",
        "fullName": "Treyvin Collum",
        "chapterGreekLetters": "Kappa Iota",
        "memberType": "Undergrad",
        "status": "Active",
        "email": "treyvincollum629@gmail.com",
        "phone": "7753649927"
      },
      {
        "firstName": "Mitchell",
        "lastName": "Cordes",
        "fullName": "Mitchell Read Cordes",
        "chapterGreekLetters": "Kappa Iota",
        "memberType": "Undergrad",
        "status": "Active",
        "email": "cordesmitchell@gmail.com",
        "phone": "(725) 502-0801"
      },
      {
        "firstName": "Joachim",
        "lastName": "Cordier",
        "fullName": "Joachim Cordier",
        "chapterGreekLetters": "Kappa Iota",
        "memberType": "Undergrad",
        "status": "Active",
        "email": "joachimcordier2@gmail.com",
        "phone": "Hidden"
      },
      {
        "firstName": "Shane",
        "lastName": "Curren",
        "fullName": "Shane Curren",
        "chapterGreekLetters": "Kappa Iota",
        "memberType": "Undergrad",
        "status": "Active",
        "email": "scurren63@gmail.com",
        "phone": "5303940697"
      },
      {
        "firstName": "Thomas",
        "lastName": "Dawson",
        "fullName": "Thomas Gilbert Dawson",
        "chapterGreekLetters": "Kappa Iota",
        "memberType": "Undergrad",
        "status": "Active",
        "email": "tommydawson2005@gmail.com",
        "phone": "7026228209"
      },
      {
        "firstName": "Jack",
        "lastName": "Deamer",
        "fullName": "Jack TR Deamer",
        "chapterGreekLetters": "Kappa Iota",
        "memberType": "Undergrad",
        "status": "Active",
        "email": "jackorjojo@gmail.com",
        "phone": "8013177885"
      },
      {
        "firstName": "William",
        "lastName": "Frederick",
        "fullName": "William Hawk Frederick",
        "chapterGreekLetters": "Kappa Iota",
        "memberType": "Undergrad",
        "status": "Active",
        "email": "hawkfrederick@yahoo.com",
        "phone": "636-577-7805"
      },
      {
        "firstName": "Robby",
        "lastName": "Gomez",
        "fullName": "Robby Niel Gomez",
        "chapterGreekLetters": "Kappa Iota",
        "memberType": "Undergrad",
        "status": "Active",
        "email": "rocknrobby12@gmail.com",
        "phone": "(702) 521-2082"
      },
      {
        "firstName": "Kyle",
        "lastName": "Johnson",
        "fullName": "Kyle Lee Johnson",
        "chapterGreekLetters": "Kappa Iota",
        "memberType": "Undergrad",
        "status": "Active",
        "email": "kyleleejohnson22@gmail.com",
        "phone": "702-556-6602"
      },
      {
        "firstName": "Jude",
        "lastName": "Landy",
        "fullName": "Jude William Landy",
        "chapterGreekLetters": "Kappa Iota",
        "memberType": "Undergrad",
        "status": "Active",
        "email": "judewlandy@icloud.com",
        "phone": "7026094191"
      },
      {
        "firstName": "Jaden",
        "lastName": "Maciel",
        "fullName": "Jaden Maciel",
        "chapterGreekLetters": "Kappa Iota",
        "memberType": "Undergrad",
        "status": "Active",
        "email": "jadenmmaciel@gmail.com",
        "phone": "7024038342"
      },
      {
        "firstName": "Seth",
        "lastName": "Manning",
        "fullName": "Seth Ryan Manning",
        "chapterGreekLetters": "Kappa Iota",
        "memberType": "Undergrad",
        "status": "Active",
        "email": "seth.manningedu@gmail.com",
        "phone": "775-293-3830"
      },
      {
        "firstName": "Logan",
        "lastName": "Martinez",
        "fullName": "Logan Martinez",
        "chapterGreekLetters": "Kappa Iota",
        "memberType": "Undergrad",
        "status": "Active",
        "email": "logan.martinez1699@gmail.com",
        "phone": "9515326997"
      },
      {
        "firstName": "Dillon",
        "lastName": "May",
        "fullName": "Dillon Armando May",
        "chapterGreekLetters": "Kappa Iota",
        "memberType": "Undergrad",
        "status": "Active",
        "email": "dillonmay50@gmail.com",
        "phone": "951-532-1920"
      },
      {
        "firstName": "Jace",
        "lastName": "Noyes",
        "fullName": "Jace Preston Noyes",
        "chapterGreekLetters": "Kappa Iota",
        "memberType": "Undergrad",
        "status": "Active",
        "email": "jace23noyes@gmail.com",
        "phone": "4358931964"
      },
      {
        "firstName": "William",
        "lastName": "Smith",
        "fullName": "William Ryan Smith",
        "chapterGreekLetters": "Kappa Iota",
        "memberType": "Undergrad",
        "status": "Active",
        "email": "william.r.smith52@gmail.com",
        "phone": "435-979-5909"
      },
      {
        "firstName": "Andrew",
        "lastName": "Strobeck",
        "fullName": "Andrew Jack Strobeck",
        "chapterGreekLetters": "Kappa Iota",
        "memberType": "Undergrad",
        "status": "Active",
        "email": "drewstrobeck@gmail.com",
        "phone": "(802) 989-6015"
      },
      {
        "firstName": "Logan",
        "lastName": "Swan",
        "fullName": "Logan william Swan",
        "chapterGreekLetters": "Kappa Iota",
        "memberType": "Undergrad",
        "status": "Active",
        "email": "loganswan55@gmail.com",
        "phone": "435-592-2895"
      },
      {
        "firstName": "Omar",
        "lastName": "Turijan",
        "fullName": "Omar Turijan",
        "chapterGreekLetters": "Kappa Iota",
        "memberType": "Undergrad",
        "status": "Active",
        "email": "omar.turijan0215@gmail.com",
        "phone": "(435) 851-7615"
      },
      {
        "firstName": "Alexander",
        "lastName": "Vega",
        "fullName": "Alexander Robert Vega",
        "chapterGreekLetters": "Kappa Iota",
        "memberType": "Undergrad",
        "status": "Active",
        "email": "vegashuskyboy@gmail.com",
        "phone": "7027863271"
      },
      {
        "firstName": "Samuel",
        "lastName": "Wang",
        "fullName": "Samuel Eric Wang",
        "chapterGreekLetters": "Kappa Iota",
        "memberType": "Undergrad",
        "status": "Active",
        "email": "sam.ewang03@gmail.com",
        "phone": "(801) 842-1747"
      },
      {
        "firstName": "Cole",
        "lastName": "Webster",
        "fullName": "Cole Adam Webster",
        "chapterGreekLetters": "Kappa Iota",
        "memberType": "Undergrad",
        "status": "Active",
        "email": "webstercole586@gmail.com",
        "phone": "385-227-2011"
      },
      {
        "firstName": "Ben",
        "lastName": "Weeg",
        "fullName": "Ben Matthew Weeg",
        "chapterGreekLetters": "Kappa Iota",
        "memberType": "Undergrad",
        "status": "Active",
        "email": "ben.weeg88@gmail.com",
        "phone": "435-531-8602"
      },
      {
        "firstName": "Alexander",
        "lastName": "Wray",
        "fullName": "Alexander Wray",
        "chapterGreekLetters": "Kappa Iota",
        "memberType": "Undergrad",
        "status": "Active",
        "email": "a.wraylovesskiing@gmail.com",
        "phone": "702-955-8007"
      }
    ]
  }
]